isspy/__init__.py
isspy/__main__.py
isspy/example_lifx.py
isspy/isspy.py
isspy/main.py
isspy-0.1.2.dist-info/LICENSE
isspy-0.1.2.dist-info/METADATA
isspy-0.1.2.dist-info/WHEEL
isspy-0.1.2.dist-info/top_level.txt
isspy-0.1.2.dist-info/RECORD
