Metadata-Version: 2.1
Name: isspy
Version: 0.1.2
Summary: Get the international space station passes over your head
Home-page: http://github.com/hydrius/isspy
Author: A Fordham
Author-email: A.fordham@iinet.net.au
License: MIT
Platform: UNKNOWN
